[
    {
        "id": "5",
        "category": "category-promotion",
        "date": "15 Mar 2022",
        "title": "Introducing the Integration Hub! We have partnered with multiple accounting platforms, so you never have to worry about manually requesting invoices and price files again!",
        "image": "https://scontent-syd2-1.xx.fbcdn.net/v/t39.30808-6/275641325_5329305027094072_3330815575755913184_n.jpg?stp=dst-jpg_p526x296&_nc_cat=103&ccb=1-5&_nc_sid=a26aad&_nc_ohc=dNUAnklLYygAX9Al8-Q&_nc_ht=scontent-syd2-1.xx&oh=00_AT8NmrTvDQg9S_ivNgjVbrH0FgdNq6E3YVP493huLoy4hg&oe=624A0849",
        "link": "https://www.facebook.com/SamiosPlumbing/posts/5329305070427401",
        "target": "_blank"
    },
    {
        "id": "4",
        "category": "category-news",
        "date": "09 Aug 2021",
        "title": "The Full Husky IVO Series Has Been Released",
        "image": "/_ui/responsive/theme-bgwt/images/news-promos/03.jpg",
        "link": "https://www.linkedin.com/posts/bgw-technologies_bgw-technologies-now-taking-orders-activity-6818657203172573184-NEjn",
        "target": "_blank"
    },
    {
        "id": "3",
        "category": "category-news",
        "date": "09 Aug 2021",
        "title": "Security Alarm change is happening QOLSYS",
        "image": "/_ui/responsive/theme-bgwt/images/news-promos/02.jpg",
        "link": "https://www.linkedin.com/posts/bgw-technologies_security-alarms-in-australia-bgw-technologies-activity-6824589065925611520-iol7",
        "target": "_blank"
    },
    {
        "id": "2",
        "category": "category-news",
        "date": "09 Aug 2021",
        "title": "Download the LATEST i-Pro Panasonic CCTV catalogue (May 2021)",
        "image": "/_ui/responsive/theme-bgwt/images/news-promos/05.jpg",
        "link": "https://www.linkedin.com/posts/bgw-technologies_panasonic-i-pro-cctv-catalogue-australia-activity-6807891366585221120-TUl6",
        "target": "_blank"
    },
    {
        "id": "1",
        "category": "category-promotion",
        "date": "09 Aug 2021",
        "title": "New Husky from Milestone Systems coming soon to BGW Technologies Australia",
        "image": "https://www.asmag.com/upload/pic/case/36278.313684.jpg",
        "link": "https://www.linkedin.com/posts/bgw-technologies_coming-soon-to-bgw-technologies-milestone-activity-6785008135573766144-pyrF",
        "target": "_blank"
    },
]
